pymmseqs-1.0.5.dist-info/METADATA
pymmseqs-1.0.5.dist-info/LICENSE
pymmseqs-1.0.5.dist-info/WHEEL
pymmseqs-1.0.5.dist-info/RECORD
pymmseqs/__init__.py
pymmseqs/commands/search.py
pymmseqs/commands/__init__.py
pymmseqs/commands/easy_cluster.py
pymmseqs/commands/createdb.py
pymmseqs/commands/fast_easy_search.py
pymmseqs/commands/easy_search.py
pymmseqs/commands/createindex.py
pymmseqs/utils/runner.py
pymmseqs/utils/utils.py
pymmseqs/utils/__init__.py
pymmseqs/utils/binary.py
pymmseqs/utils/tools_utils.py
pymmseqs/config/easy_search_config.py
pymmseqs/config/base.py
pymmseqs/config/createdb_config.py
pymmseqs/config/createtaxdb_config.py
pymmseqs/config/createindex_config.py
pymmseqs/config/__init__.py
pymmseqs/config/search_config.py
pymmseqs/config/touchdb_config.py
pymmseqs/config/align_config.py
pymmseqs/config/convertalis_config.py
pymmseqs/config/easy_cluster_config.py
pymmseqs/config/easy_linsearch_config.py
pymmseqs/config/easy_linclust_config.py
pymmseqs/tools/__init__.py
pymmseqs/tools/easy_cluster_tools.py
pymmseqs/bin/__init__.py
pymmseqs/bin/mmseqs
pymmseqs/defaults/search.yaml
pymmseqs/defaults/touchdb.yaml
pymmseqs/defaults/createindex.yaml
pymmseqs/defaults/easy_cluster.yaml
pymmseqs/defaults/convertalis.yaml
pymmseqs/defaults/easy_linclust.yaml
pymmseqs/defaults/__init__.py
pymmseqs/defaults/createdb.yaml
pymmseqs/defaults/easy_search.yaml
pymmseqs/defaults/align.yaml
pymmseqs/defaults/easy_linsearch.yaml
pymmseqs/defaults/createtaxdb.yaml
pymmseqs/parsers/easy_cluster_parser.py
pymmseqs/parsers/createdb_parser.py
pymmseqs/parsers/__init__.py
pymmseqs/parsers/search_parser.py
pymmseqs/parsers/easy_search_parser.py
pymmseqs/parsers/createindex_parser.py
