Metadata-Version: 2.3
Name: pymmseqs
Version: 1.0.5
Summary: Python wrapper for MMseqs2
License: MIT
Author: heispv
Author-email: peyman.vahidi@tum.de
Requires-Python: >=3.10
Classifier: License :: OSI Approved :: MIT License
Classifier: Operating System :: MacOS :: MacOS X
Classifier: Operating System :: POSIX :: Linux
Classifier: Programming Language :: Python :: 3
Classifier: Programming Language :: Python :: 3.10
Classifier: Programming Language :: Python :: 3.11
Classifier: Programming Language :: Python :: 3.12
Classifier: Programming Language :: Python :: 3.13
Requires-Dist: ipython (>=8.22.1,<9.0.0)
Requires-Dist: numpy (>=1.22.4)
Requires-Dist: pandas (>=2.2.2,<3.0.0)
Requires-Dist: pyyaml (>=6.0.1,<7.0.0)
Project-URL: Bug Tracker, https://github.com/heispv/pymmseqs/issues
Project-URL: Documentation, https://github.com/heispv/pymmseqs/wiki
Project-URL: Homepage, https://github.com/heispv/pymmseqs
